madblockscloud/__init__.py
madblockscloud/mbaws.py
madblockscloud/mbcloud.py
madblockscloud/mbibm.py
madblockscloud/mbmail.py
madblockscloud/mbotp.py
madblockscloud/thingspeak.py
madblockscloud-1.0.dist-info/METADATA
madblockscloud-1.0.dist-info/WHEEL
madblockscloud-1.0.dist-info/top_level.txt
madblockscloud-1.0.dist-info/RECORD
