Metadata-Version: 2.1
Name: madblockscloud
Version: 1.0
Summary: madBlocks Cloud Library
Home-page: https://upload.pypi.org/legacy/
Author: Surya Kumar V
Author-email: orl.suryakumar@gmail.com
License: MIT
Platform: UNKNOWN
